pptestpiotrekpieron/__init__.py
pptestpiotrekpieron/m_mod_pptest.py
pptestpiotrekpieron-0.0.4.dist-info/LICENCE.txt
pptestpiotrekpieron-0.0.4.dist-info/METADATA
pptestpiotrekpieron-0.0.4.dist-info/WHEEL
pptestpiotrekpieron-0.0.4.dist-info/top_level.txt
pptestpiotrekpieron-0.0.4.dist-info/RECORD
