Metadata-Version: 2.1
Name: pptestpiotrekpieron
Version: 0.0.4
Summary: My test package
Author-email: PP <piotrek.pieron@gmail.com>
License: MIT License
Keywords: pptestpiotrekpieron,funny functions,name,surname,personal data
Classifier: Development Status :: 4 - Beta
Classifier: Environment :: GPU
Requires-Python: >=3.0
License-File: LICENCE.txt
Requires-Dist: numpy ; python_version >= "3.0"
